{
  "id": "U0AHPQDJ0DA",
  "name": "logan.herzog",
  "is_bot": false,
  "updated": 1772547376,
  "is_app_user": false,
  "team_id": "T012H3JSC83",
  "deleted": false,
  "color": "4cc091",
  "is_email_confirmed": true,
  "real_name": "Logan Herzog",
  "tz": "America/Chicago",
  "tz_label": "Central Daylight Time",
  "tz_offset": -18000,
  "is_admin": false,
  "is_owner": false,
  "is_primary_owner": false,
  "is_restricted": false,
  "is_ultra_restricted": false,
  "who_can_share_contact_card": "EVERYONE",
  "profile": {
    "real_name": "Logan Herzog",
    "display_name": "Logan Herzog",
    "avatar_hash": "g8041568e36c",
    "real_name_normalized": "Logan Herzog",
    "display_name_normalized": "Logan Herzog",
    "image_24": "https://secure.gravatar.com/avatar/8041568e36c1438393d328ccb43a687c.jpg?s=24&d=https%3A%2F%2Fa.slack-edge.com%2Fdf10d%2Fimg%2Favatars%2Fava_0011-24.png",
    "image_32": "https://secure.gravatar.com/avatar/8041568e36c1438393d328ccb43a687c.jpg?s=32&d=https%3A%2F%2Fa.slack-edge.com%2Fdf10d%2Fimg%2Favatars%2Fava_0011-32.png",
    "image_48": "https://secure.gravatar.com/avatar/8041568e36c1438393d328ccb43a687c.jpg?s=48&d=https%3A%2F%2Fa.slack-edge.com%2Fdf10d%2Fimg%2Favatars%2Fava_0011-48.png",
    "image_72": "https://secure.gravatar.com/avatar/8041568e36c1438393d328ccb43a687c.jpg?s=72&d=https%3A%2F%2Fa.slack-edge.com%2Fdf10d%2Fimg%2Favatars%2Fava_0011-72.png",
    "image_192": "https://secure.gravatar.com/avatar/8041568e36c1438393d328ccb43a687c.jpg?s=192&d=https%3A%2F%2Fa.slack-edge.com%2Fdf10d%2Fimg%2Favatars%2Fava_0011-192.png",
    "image_512": "https://secure.gravatar.com/avatar/8041568e36c1438393d328ccb43a687c.jpg?s=512&d=https%3A%2F%2Fa.slack-edge.com%2Fdf10d%2Fimg%2Favatars%2Fava_0011-512.png",
    "first_name": "Logan",
    "last_name": "Herzog",
    "team": "T012H3JSC83",
    "title": "",
    "phone": "",
    "skype": "",
    "status_text": "",
    "status_text_canonical": "",
    "status_emoji": "",
    "status_emoji_display_info": [],
    "status_expiration": 0
  }
}
